funowl/ImplementationNotes.md
funowl/__init__.py
funowl/annotations.py
funowl/assertions.py
funowl/axioms.py
funowl/class_axioms.py
funowl/class_expressions.py
funowl/cli.py
funowl/dataproperty_axioms.py
funowl/dataproperty_expressions.py
funowl/dataranges.py
funowl/declarations.py
funowl/general_definitions.py
funowl/identifiers.py
funowl/individuals.py
funowl/literals.py
funowl/objectproperty_axioms.py
funowl/objectproperty_expressions.py
funowl/ontology_document.py
funowl/prefix_declarations.py
funowl/base/__init__.py
funowl/base/cast_function.py
funowl/base/clone_subgraph.py
funowl/base/fun_owl_base.py
funowl/base/fun_owl_choice.py
funowl/base/list_support.py
funowl/base/rdftriple.py
funowl/converters/__init__.py
funowl/converters/functional_converter.py
funowl/converters/rdf_converter.py
funowl/terminals/Patterns.py
funowl/terminals/Terminals.py
funowl/terminals/TypingHelper.py
funowl/terminals/__init__.py
funowl/writers/FunctionalWriter.py
funowl/writers/__init__.py
funowl-0.2.3.dist-info/AUTHORS
funowl-0.2.3.dist-info/LICENSE
funowl-0.2.3.dist-info/METADATA
funowl-0.2.3.dist-info/WHEEL
funowl-0.2.3.dist-info/entry_points.txt
funowl-0.2.3.dist-info/pbr.json
funowl-0.2.3.dist-info/top_level.txt
funowl-0.2.3.dist-info/RECORD
