Metadata-Version: 2.1
Name: funowl
Version: 0.2.3
Summary: Python rendering of the OWL Functional syntax
Home-page: http://biolink.github.io/hsolbrig
Author: Harold Solbrig
Author-email: solbrig@jhu.edu
License: CC0 1.0 Universal
Keywords: OWL,ontology,web,functional syntax,python
Classifier: Development Status :: 3 - Alpha
Classifier: Environment :: Console
Classifier: Intended Audience :: Developers
Classifier: Intended Audience :: Science/Research
Classifier: Intended Audience :: Healthcare Industry
Classifier: License :: CC0 1.0 Universal (CC0 1.0) Public Domain Dedication
Classifier: Programming Language :: Python :: 3 :: Only
Classifier: Programming Language :: Python :: 3.8
Classifier: Programming Language :: Python :: 3.9
Requires-Python: >=3.7
License-File: LICENSE
License-File: AUTHORS
Requires-Dist: bcp47
Requires-Dist: jsonasobj
Requires-Dist: pyjsg (>=0.11.6)
Requires-Dist: rdflib-shim
Requires-Dist: rdflib (<8,>=6.2.0)
Requires-Dist: rfc3987
